rotational_update/__init__.py
rotational_update/layers/__init__.py
rotational_update/layers/base.py
rotational_update/layers/static.py
rotational_update/layers/functions/__init__.py
rotational_update/layers/functions/static.py
rotational_update-0.0.18.dist-info/LICENSE
rotational_update-0.0.18.dist-info/METADATA
rotational_update-0.0.18.dist-info/WHEEL
rotational_update-0.0.18.dist-info/top_level.txt
rotational_update-0.0.18.dist-info/RECORD
