Metadata-Version: 2.1
Name: rotational-update
Version: 0.0.18
Summary: Rotational_update module for PyTorch
Home-page: https://github.com/ryhoh/Rotational_update
Author: Tetsuya Hori
Author-email: hori.t3t@gmail.com
License: MIT
Keywords: rotational rotational-update
Platform: UNKNOWN
Classifier: License :: OSI Approved :: MIT License
Classifier: Programming Language :: Python :: 3.6
Classifier: Programming Language :: Python :: 3.7
License-File: LICENSE
Requires-Dist: torch (>=1.3.0)
Requires-Dist: torchvision (>=0.4.1)
